{
  "_meta": {
    "version": "1.0.0",
    "lastUpdated": "<YYYY-MM-DD>",
    "description": "Redacted template. Copy to profile.local.json (gitignored) and fill with your real values. Sprint 10A §10-2."
  },

  "jose": {
    "netPitiGreen": 0,
    "netPitiYellow": 0,
    "netPitiRed": 0,
    "cashCloseGreen": 0,
    "cashCloseRed": 0,
    "rehabGreen": 0,
    "rehabYellow": 0,
    "rehabRed": 0,
    "priceCeilingDuplex": 0,
    "priceCeilingTriplex": 0,
    "maxDtiPct": 45,
    "roofAgeYellow": 15,
    "enforceOldHouseGates": false,
    "enforceZipTierAsHardFail": false,
    "schoolRatingMinimum": 4,
    "schoolRatingYellowThreshold": 5,
    "schoolRatingGreenThreshold": 7,
    "schoolRatingResaleWeight": 0.15
  },

  "location": {
    "homeBase": { "name": "", "lat": 0, "lng": 0 },
    "maxMilesHard": 35,
    "enforceMaxMilesAsHardFail": true,
    "_doc": "Haversine radius from homeBase. Sprint 12-2 gates verdict on it; Sprint 14.5 added `enforceMaxMilesAsHardFail` — set false to make ALL geography checks informational-only (both `maxMilesHard` AND `zipTiers.conditionalCities` distance thresholds). `zipTiers.excludedCities` is a separate static check and stays on."
  },

  "rentalStrategy": {
    "primary": "LTR",
    "consideredSecondary": "MTR",
    "strExcluded": true,
    "vacancyPct": 5,
    "vacancyPctMtr": 12,
    "rentMultiplierMtr": 1.35,
    "mtrMinLandlordMonths": 12,
    "_doc": "MTR rents credited only once landlord months ≥ mtrMinLandlordMonths. Sprint 12-3."
  },

  "selfManagement": {
    "selfManageCap": 3,
    "propertyManagementTriggerUnits": 4,
    "propertyManagementFallbackPct": 9,
    "_doc": "When units >= trigger AND not self-managed, PITI math auto-injects fallback PM %. Sprint 12-4."
  },

  "contractorStretch": {
    "enabled": false,
    "maxRehab": 150000,
    "selfPerformMinPct": 40,
    "_doc": "Activates 203(k) scenarios when rehab > rehabRed AND self-perform share >= minPct. Sprint 12-5."
  },

  "defaults": {
    "buyerAnnualIncomeW2": 0,
    "buyerMonthlyIncomeW2": 0,
    "seIncomeForQualifying": 0,
    "creditScore": 0,
    "monthlyDebts": 0,
    "downPaymentPct": 3.5,
    "loanType": "FHA",
    "loanTerm": 30,
    "interestRate": 6.5,
    "fhaUpfrontMipPct": 1.75,
    "fhaAnnualMipPct": 0.55,
    "propertyTaxRatePct": 1.1,
    "insuranceAnnual": 1800,
    "hoaMonthly": 0,
    "vacancyPct": 5,
    "maintenancePct": 5,
    "propertyManagementPct": 0,
    "ownerOccupied": true,
    "unitsOccupiedByOwner": 1,
    "closingCostsPct": 3,
    "rentalOffsetPct": 75,
    "maxDtiPct": 45,
    "maxNetPitiTarget": 0,
    "maxCashToClose": 0,
    "reserveMonths": 2,
    "selfPerformRoofing": false,
    "roofingCostMultiplier": 1.0,
    "targetMonthlyRent": 0,
    "defaultPreset": "Vallejo Priority",
    "scanTopNPerZip": 10
  }
}
